{"chunk_definitions":[{"chunk_id":"ctnb7dhdoon50","chunk_label":"setup","document_id":null,"expansion_state":0,"options":{"engine":"r","include":false,"label":"setup"},"row":26,"row_count":1,"visible":true},{"chunk_id":"cwiucnvf1e73w","chunk_label":"unnamed-chunk-1","document_id":"FD141A1D","expansion_state":0,"options":{"engine":"r","label":"unnamed-chunk-12"},"row":58,"row_count":1,"visible":true},{"chunk_id":"c47quqphbm3ol","chunk_label":"unnamed-chunk-2","document_id":"FD141A1D","expansion_state":0,"options":{"engine":"r","label":"unnamed-chunk-32"},"row":128,"row_count":1,"visible":true},{"chunk_id":"cz4oq8s1o6o3g","chunk_label":"unnamed-chunk-3","document_id":"FD141A1D","expansion_state":0,"options":{"engine":"r","label":"unnamed-chunk-89"},"row":289,"row_count":1,"visible":true},{"chunk_id":"cb146nas1jnp5","chunk_label":"unnamed-chunk-4","document_id":"89F65769","expansion_state":0,"options":{"engine":"r","label":"unnamed-chunk-15"},"row":417,"row_count":1,"visible":true}],"doc_write_time":1604682842}